pyanimecli/__init__.py
pyanimecli/__main__.py
pyanimecli/pyanimecli.py
pyanimecli-1.2.1.dist-info/licenses/LICENSE
pyanimecli-1.2.1.dist-info/METADATA
pyanimecli-1.2.1.dist-info/WHEEL
pyanimecli-1.2.1.dist-info/entry_points.txt
pyanimecli-1.2.1.dist-info/top_level.txt
pyanimecli-1.2.1.dist-info/RECORD
