Metadata-Version: 2.4
Name: pyanimecli
Version: 1.2.1
Summary: A powerful command-line interface for searching, getting info, and watching anime directly from your terminal.
Author-email: Gamma <Gamma.scratch@gmail.com>
License: MIT
Project-URL: Homepage, https://github.com/Gamma7113131/pyanimecli
Project-URL: Source, https://github.com/Gamma7113131/pyanimecli
Project-URL: Tracker, https://github.com/Gamma7113131/pyanimecli/issues
License-File: LICENSE
Requires-Dist: requests
Requires-Dist: rich
Requires-Dist: pym3u8downloader
Requires-Dist: packaging
Requires-Dist: tqdm
Dynamic: license-file
